{
  "timestamp": "2026-02-06T06:51:02.812296729-08:00",
  "games": {
    "02816abf-e5c9-4a99-a64e-3661da0a257b": {
      "game": {
        "id": "02816abf-e5c9-4a99-a64e-3661da0a257b",
        "player1Leader": {
          "id": "LAW_012"
        },
        "player1Base": {
          "id": "JTL_030"
        },
        "player2Leader": {
          "id": "LAW_005"
        },
        "player2Base": {
          "id": "JTL_026"
        },
        "format": "nextSetPreview"
      },
      "startTime": "2026-02-06T06:50:07.774584901-08:00"
    },
    "0606231b-5e75-4b53-8e0c-e556e2ca8106": {
      "game": {
        "id": "0606231b-5e75-4b53-8e0c-e556e2ca8106",
        "player1Leader": {
          "id": "SOR_017"
        },
        "player1Base": {
          "id": "SOR_022"
        },
        "player2Leader": {
          "id": "LOF_004"
        },
        "player2Base": {
          "id": "JTL_030"
        },
        "format": "premier"
      },
      "startTime": "2026-02-06T06:49:02.626682543-08:00"
    },
    "06abf5be-b63a-4dc6-ac10-592077527509": {
      "game": {
        "id": "06abf5be-b63a-4dc6-ac10-592077527509",
        "player1Leader": {
          "id": "JTL_003"
        },
        "player1Base": {
          "id": "JTL_024"
        },
        "player2Leader": {
          "id": "SOR_006"
        },
        "player2Base": {
          "id": "SHD_026"
        },
        "format": "premier"
      },
      "startTime": "2026-02-06T06:45:04.928658509-08:00"
    },
    "08696e93-920f-467f-a192-2cd83c8ac04e": {
      "game": {
        "id": "08696e93-920f-467f-a192-2cd83c8ac04e",
        "player1Leader": {
          "id": "JTL_016"
        },
        "player1Base": {
          "id": "TWI_030"
        },
        "player2Leader": {
          "id": "SEC_002"
        },
        "player2Base": {
          "id": "JTL_024"
        },
        "format": "premier"
      },
      "startTime": "2026-02-06T06:45:04.928658509-08:00"
    },
    "0e6f8391-f60b-40c9-b1cc-86aee7f5f32e": {
      "game": {
        "id": "0e6f8391-f60b-40c9-b1cc-86aee7f5f32e",
        "player1Leader": {
          "id": "SHD_001"
        },
        "player1Base": {
          "id": "SOR_022"
        },
        "player2Leader": {
          "id": "SHD_011"
        },
        "player2Base": {
          "id": "SOR_025"
        },
        "format": "premier"
      },
      "startTime": "2026-02-06T06:50:07.774584901-08:00"
    },
    "0f6020f8-f00b-41b8-9952-f4eb7093b9c8": {
      "game": {
        "id": "0f6020f8-f00b-41b8-9952-f4eb7093b9c8",
        "player1Leader": {
          "id": "TWI_003"
        },
        "player1Base": {
          "id": "SOR_022"
        },
        "player2Leader": {
          "id": "JTL_005"
        },
        "player2Base": {
          "id": "SHD_024"
        },
        "format": "premier"
      },
      "startTime": "2026-02-06T06:49:02.626682543-08:00"
    },
    "11a7f18e-182d-4789-aa39-afaa64026b60": {
      "game": {
        "id": "11a7f18e-182d-4789-aa39-afaa64026b60",
        "player1Leader": {
          "id": "SHD_013"
        },
        "player1Base": {
          "id": "SOR_022"
        },
        "player2Leader": {
          "id": "JTL_012"
        },
        "player2Base": {
          "id": "JTL_024"
        },
        "format": "premier"
      },
      "startTime": "2026-02-06T06:49:02.626682543-08:00"
    },
    "1268b5e1-be1d-43b7-8747-43cc7b9eb146": {
      "game": {
        "id": "1268b5e1-be1d-43b7-8747-43cc7b9eb146",
        "player1Leader": {
          "id": "SOR_002"
        },
        "player1Base": {
          "id": "SHD_019"
        },
        "player2Leader": {
          "id": "LOF_009"
        },
        "player2Base": {
          "id": "LOF_021"
        },
        "format": "premier"
      },
      "startTime": "2026-02-06T06:48:03.57065742-08:00"
    },
    "154bc159-e40a-455c-bda3-2d919f980893": {
      "game": {
        "id": "154bc159-e40a-455c-bda3-2d919f980893",
        "player1Leader": {
          "id": "LAW_014"
        },
        "player1Base": {
          "id": "LOF_020"
        },
        "player2Leader": {
          "id": "LAW_018"
        },
        "player2Base": {
          "id": "JTL_024"
        },
        "format": "nextSetPreview"
      },
      "startTime": "2026-02-06T06:44:10.039465841-08:00"
    },
    "175db5b8-8045-42d9-abf6-427cedeb4f81": {
      "game": {
        "id": "175db5b8-8045-42d9-abf6-427cedeb4f81",
        "player1Leader": {
          "id": "SOR_006"
        },
        "player1Base": {
          "id": "SHD_026"
        },
        "player2Leader": {
          "id": "LOF_001"
        },
        "player2Base": {
          "id": "JTL_024"
        },
        "format": "premier"
      },
      "startTime": "2026-02-06T06:41:03.813659592-08:00"
    },
    "188aaf8f-1678-4ba6-9cfa-f5f08a6c78db": {
      "game": {
        "id": "188aaf8f-1678-4ba6-9cfa-f5f08a6c78db",
        "player1Leader": {
          "id": "JTL_005"
        },
        "player1Base": {
          "id": "TWI_020"
        },
        "player2Leader": {
          "id": "JTL_006"
        },
        "player2Base": {
          "id": "SOR_029"
        },
        "format": "premier"
      },
      "startTime": "2026-02-06T06:51:02.812296729-08:00"
    },
    "1973f40d-3812-43de-a310-4b42e1d43cf9": {
      "game": {
        "id": "1973f40d-3812-43de-a310-4b42e1d43cf9",
        "player1Leader": {
          "id": "JTL_005"
        },
        "player1Base": {
          "id": "JTL_026"
        },
        "player2Leader": {
          "id": "SHD_013"
        },
        "player2Base": {
          "id": "LOF_021"
        },
        "format": "premier"
      },
      "startTime": "2026-02-06T06:41:03.813659592-08:00"
    },
    "1bfb474a-985b-401a-bef2-799f9f012e17": {
      "game": {
        "id": "1bfb474a-985b-401a-bef2-799f9f012e17",
        "player1Leader": {
          "id": "TWI_004"
        },
        "player1Base": {
          "id": "SEC_022"
        },
        "player2Leader": {
          "id": "TWI_014"
        },
        "player2Base": {
          "id": "TWI_022"
        },
        "format": "premier"
      },
      "startTime": "2026-02-06T06:44:10.039465841-08:00"
    },
    "1cdc4ef6-6291-4326-a5cd-6717e5513299": {
      "game": {
        "id": "1cdc4ef6-6291-4326-a5cd-6717e5513299",
        "player1Leader": {
          "id": "SEC_012"
        },
        "player1Base": {
          "id": "SOR_030"
        },
        "player2Leader": {
          "id": "JTL_009"
        },
        "player2Base": {
          "id": "SEC_025"
        },
        "format": "nextSetPreview"
      },
      "startTime": "2026-02-06T06:49:02.626682543-08:00"
    },
    "1e54e1fd-e657-4d39-b316-3d58f51c5af7": {
      "game": {
        "id": "1e54e1fd-e657-4d39-b316-3d58f51c5af7",
        "player1Leader": {
          "id": "SEC_010"
        },
        "player1Base": {
          "id": "SOR_030"
        },
        "player2Leader": {
          "id": "JTL_009"
        },
        "player2Base": {
          "id": "SOR_029"
        },
        "format": "premier"
      },
      "startTime": "2026-02-06T06:49:02.626682543-08:00"
    },
    "200828c6-5390-415b-a57d-b7751b5ff2fe": {
      "game": {
        "id": "200828c6-5390-415b-a57d-b7751b5ff2fe",
        "player1Leader": {
          "id": "JTL_015"
        },
        "player1Base": {
          "id": "SOR_025"
        },
        "player2Leader": {
          "id": "SOR_014"
        },
        "player2Base": {
          "id": "SOR_022"
        },
        "format": "premier"
      },
      "startTime": "2026-02-06T06:50:07.774584901-08:00"
    },
    "2540952f-0d45-4773-9af7-2e60316eab05": {
      "game": {
        "id": "2540952f-0d45-4773-9af7-2e60316eab05",
        "player1Leader": {
          "id": "SHD_002"
        },
        "player1Base": {
          "id": "JTL_024"
        },
        "player2Leader": {
          "id": "TWI_012"
        },
        "player2Base": {
          "id": "SEC_019"
        },
        "format": "premier"
      },
      "startTime": "2026-02-06T06:48:03.57065742-08:00"
    },
    "2556a6f7-e8bf-437a-bd3f-3b098e4983be": {
      "game": {
        "id": "2556a6f7-e8bf-437a-bd3f-3b098e4983be",
        "player1Leader": {
          "id": "TWI_018"
        },
        "player1Base": {
          "id": "SOR_025"
        },
        "player2Leader": {
          "id": "LOF_008"
        },
        "player2Base": {
          "id": "LOF_019"
        },
        "format": "open"
      },
      "startTime": "2026-02-06T06:46:07.003766694-08:00"
    },
    "29542703-a991-42d8-bf37-3fe9618ff791": {
      "game": {
        "id": "29542703-a991-42d8-bf37-3fe9618ff791",
        "player1Leader": {
          "id": "SHD_014"
        },
        "player1Base": {
          "id": "SOR_025"
        },
        "player2Leader": {
          "id": "JTL_005"
        },
        "player2Base": {
          "id": "JTL_026"
        },
        "format": "premier"
      },
      "startTime": "2026-02-06T06:45:04.928658509-08:00"
    },
    "29df0da2-7c5e-4019-b6c1-86edaecf400e": {
      "game": {
        "id": "29df0da2-7c5e-4019-b6c1-86edaecf400e",
        "player1Leader": {
          "id": "SHD_013"
        },
        "player1Base": {
          "id": "SOR_022"
        },
        "player2Leader": {
          "id": "JTL_010"
        },
        "player2Base": {
          "id": "JTL_024"
        },
        "format": "premier"
      },
      "startTime": "2026-02-06T06:48:03.57065742-08:00"
    },
    "35ed3f9e-bd65-461f-8790-0d059dda667d": {
      "game": {
        "id": "35ed3f9e-bd65-461f-8790-0d059dda667d",
        "player1Leader": {
          "id": "SOR_006"
        },
        "player1Base": {
          "id": "SHD_026"
        },
        "player2Leader": {
          "id": "SHD_014"
        },
        "player2Base": {
          "id": "SOR_025"
        },
        "format": "premier"
      },
      "startTime": "2026-02-06T06:47:04.743988839-08:00"
    },
    "36cf2454-00f9-493d-b7c3-bbda00b37b5f": {
      "game": {
        "id": "36cf2454-00f9-493d-b7c3-bbda00b37b5f",
        "player1Leader": {
          "id": "SHD_013"
        },
        "player1Base": {
          "id": "SOR_022"
        },
        "player2Leader": {
          "id": "JTL_005"
        },
        "player2Base": {
          "id": "SOR_026"
        },
        "format": "premier"
      },
      "startTime": "2026-02-06T06:50:07.774584901-08:00"
    },
    "3763f491-f696-4df8-a597-411d5e582ba7": {
      "game": {
        "id": "3763f491-f696-4df8-a597-411d5e582ba7",
        "player1Leader": {
          "id": "LOF_009"
        },
        "player1Base": {
          "id": "LOF_020"
        },
        "player2Leader": {
          "id": "SHD_013"
        },
        "player2Base": {
          "id": "JTL_024"
        },
        "format": "premier"
      },
      "startTime": "2026-02-06T06:46:07.003766694-08:00"
    },
    "37a2949b-edd8-4cb5-bf88-558d4b7cece6": {
      "game": {
        "id": "37a2949b-edd8-4cb5-bf88-558d4b7cece6",
        "player1Leader": {
          "id": "SEC_017"
        },
        "player1Base": {
          "id": "SOR_030"
        },
        "player2Leader": {
          "id": "LOF_006"
        },
        "player2Base": {
          "id": "SHD_025"
        },
        "format": "premier"
      },
      "startTime": "2026-02-06T06:33:01.097488631-08:00"
    },
    "39c14609-f0ea-4277-be6f-28d1f29d7515": {
      "game": {
        "id": "39c14609-f0ea-4277-be6f-28d1f29d7515",
        "player1Leader": {
          "id": "SHD_002"
        },
        "player1Base": {
          "id": "JTL_024"
        },
        "player2Leader": {
          "id": "SOR_017"
        },
        "player2Base": {
          "id": "LOF_021"
        },
        "format": "premier"
      },
      "startTime": "2026-02-06T06:34:59.88043442-08:00"
    },
    "41065cdc-1e56-423d-a2ef-cc173bc959c4": {
      "game": {
        "id": "41065cdc-1e56-423d-a2ef-cc173bc959c4",
        "player1Leader": {
          "id": "SEC_010"
        },
        "player1Base": {
          "id": "JTL_020"
        },
        "player2Leader": {
          "id": "SEC_016"
        },
        "player2Base": {
          "id": "SOR_025"
        },
        "format": "premier"
      },
      "startTime": "2026-02-06T06:47:04.743988839-08:00"
    },
    "427e9bce-94f8-4b5b-860e-6fc0d3d02d5a": {
      "game": {
        "id": "427e9bce-94f8-4b5b-860e-6fc0d3d02d5a",
        "player1Leader": {
          "id": "SHD_010"
        },
        "player1Base": {
          "id": "JTL_024"
        },
        "player2Leader": {
          "id": "LOF_006"
        },
        "player2Base": {
          "id": "SOR_030"
        },
        "format": "premier"
      },
      "startTime": "2026-02-06T06:47:04.743988839-08:00"
    },
    "467ec3d6-4712-4cb7-9250-1cb7af9d23a6": {
      "game": {
        "id": "467ec3d6-4712-4cb7-9250-1cb7af9d23a6",
        "player1Leader": {
          "id": "LOF_008"
        },
        "player1Base": {
          "id": "LOF_019"
        },
        "player2Leader": {
          "id": "LAW_018"
        },
        "player2Base": {
          "id": "JTL_024"
        },
        "format": "nextSetPreview"
      },
      "startTime": "2026-02-06T06:45:04.928658509-08:00"
    },
    "4a79616a-5d45-4858-9022-ca5644998a00": {
      "game": {
        "id": "4a79616a-5d45-4858-9022-ca5644998a00",
        "player1Leader": {
          "id": "JTL_011"
        },
        "player1Base": {
          "id": "SOR_029"
        },
        "player2Leader": {
          "id": "JTL_009"
        },
        "player2Base": {
          "id": "JTL_024"
        },
        "format": "premier"
      },
      "startTime": "2026-02-06T06:47:04.743988839-08:00"
    },
    "4ac81e21-0bce-442d-8ea3-458d2e383390": {
      "game": {
        "id": "4ac81e21-0bce-442d-8ea3-458d2e383390",
        "player1Leader": {
          "id": "SOR_017"
        },
        "player1Base": {
          "id": "SOR_025"
        },
        "player2Leader": {
          "id": "SEC_014"
        },
        "player2Base": {
          "id": "JTL_024"
        },
        "format": "premier"
      },
      "startTime": "2026-02-06T06:47:04.743988839-08:00"
    },
    "4c339929-18e8-42dc-9f8f-67a145411ee5": {
      "game": {
        "id": "4c339929-18e8-42dc-9f8f-67a145411ee5",
        "player1Leader": {
          "id": "JTL_012"
        },
        "player1Base": {
          "id": "JTL_024"
        },
        "player2Leader": {
          "id": "LOF_009"
        },
        "player2Base": {
          "id": "LOF_020"
        },
        "format": "nextSetPreview"
      },
      "startTime": "2026-02-06T06:51:02.812296729-08:00"
    },
    "4d106de7-d054-465f-bfb3-853df9005da4": {
      "game": {
        "id": "4d106de7-d054-465f-bfb3-853df9005da4",
        "player1Leader": {
          "id": "LAW_011"
        },
        "player1Base": {
          "id": "JTL_019"
        },
        "player2Leader": {
          "id": "LAW_009"
        },
        "player2Base": {
          "id": "JTL_019"
        },
        "format": "nextSetPreview"
      },
      "startTime": "2026-02-06T06:47:04.743988839-08:00"
    },
    "4d2279bc-28d2-49e9-befb-6b177457e189": {
      "game": {
        "id": "4d2279bc-28d2-49e9-befb-6b177457e189",
        "player1Leader": {
          "id": "JTL_012"
        },
        "player1Base": {
          "id": "SOR_024"
        },
        "player2Leader": {
          "id": "SEC_012"
        },
        "player2Base": {
          "id": "SEC_022"
        },
        "format": "premier"
      },
      "startTime": "2026-02-06T06:51:02.812296729-08:00"
    },
    "4efbc94d-9b6b-4735-be07-8d80e926fbbd": {
      "game": {
        "id": "4efbc94d-9b6b-4735-be07-8d80e926fbbd",
        "player1Leader": {
          "id": "LOF_007"
        },
        "player1Base": {
          "id": "LOF_020"
        },
        "player2Leader": {
          "id": "LOF_001"
        },
        "player2Base": {
          "id": "LOF_026"
        },
        "format": "premier"
      },
      "startTime": "2026-02-06T06:48:03.57065742-08:00"
    },
    "4fb4f3c6-da13-4fb1-83f7-cb6c5a8f952d": {
      "game": {
        "id": "4fb4f3c6-da13-4fb1-83f7-cb6c5a8f952d",
        "player1Leader": {
          "id": "JTL_006"
        },
        "player1Base": {
          "id": "TWI_030"
        },
        "player2Leader": {
          "id": "JTL_013"
        },
        "player2Base": {
          "id": "JTL_024"
        },
        "format": "premier"
      },
      "startTime": "2026-02-06T06:51:02.812296729-08:00"
    },
    "567cc2c3-ea83-4004-8138-2feccc255d6d": {
      "game": {
        "id": "567cc2c3-ea83-4004-8138-2feccc255d6d",
        "player1Leader": {
          "id": "JTL_016"
        },
        "player1Base": {
          "id": "SOR_024"
        },
        "player2Leader": {
          "id": "LAW_014"
        },
        "player2Base": {
          "id": "SHD_026"
        },
        "format": "open"
      },
      "startTime": "2026-02-06T06:50:07.774584901-08:00"
    },
    "5ec95a68-ef98-430d-b29f-43af277d5f2a": {
      "game": {
        "id": "5ec95a68-ef98-430d-b29f-43af277d5f2a",
        "player1Leader": {
          "id": "JTL_011"
        },
        "player1Base": {
          "id": "JTL_028"
        },
        "player2Leader": {
          "id": "JTL_011"
        },
        "player2Base": {
          "id": "SOR_030"
        },
        "format": "nextSetPreview"
      },
      "startTime": "2026-02-06T06:50:07.774584901-08:00"
    },
    "607c5bed-6162-4588-b881-458a8998d39c": {
      "game": {
        "id": "607c5bed-6162-4588-b881-458a8998d39c",
        "player1Leader": {
          "id": "LOF_006"
        },
        "player1Base": {
          "id": "JTL_020"
        },
        "player2Leader": {
          "id": "SEC_017"
        },
        "player2Base": {
          "id": "JTL_024"
        },
        "format": "nextSetPreview"
      },
      "startTime": "2026-02-06T06:50:07.774584901-08:00"
    },
    "62608bfc-6101-4e53-a5a4-3ffe9c3167ee": {
      "game": {
        "id": "62608bfc-6101-4e53-a5a4-3ffe9c3167ee",
        "player1Leader": {
          "id": "TWI_017"
        },
        "player1Base": {
          "id": "TWI_021"
        },
        "player2Leader": {
          "id": "TWI_004"
        },
        "player2Base": {
          "id": "JTL_028"
        },
        "format": "premier"
      },
      "startTime": "2026-02-06T06:49:02.626682543-08:00"
    },
    "64613e32-1f06-4864-b3b5-9b6cda943d65": {
      "game": {
        "id": "64613e32-1f06-4864-b3b5-9b6cda943d65",
        "player1Leader": {
          "id": "TWI_017"
        },
        "player1Base": {
          "id": "LOF_021"
        },
        "player2Leader": {
          "id": "LOF_009"
        },
        "player2Base": {
          "id": "LOF_020"
        },
        "format": "premier"
      },
      "startTime": "2026-02-06T06:48:03.57065742-08:00"
    },
    "666c8b01-c37f-48d1-8121-7490a5341e29": {
      "game": {
        "id": "666c8b01-c37f-48d1-8121-7490a5341e29",
        "player1Leader": {
          "id": "SEC_010"
        },
        "player1Base": {
          "id": "SEC_025"
        },
        "player2Leader": {
          "id": "JTL_013"
        },
        "player2Base": {
          "id": "JTL_024"
        },
        "format": "nextSetPreview"
      },
      "startTime": "2026-02-06T06:50:07.774584901-08:00"
    },
    "694f5d7e-ca09-4d81-8eda-39e276ddbb64": {
      "game": {
        "id": "694f5d7e-ca09-4d81-8eda-39e276ddbb64",
        "player1Leader": {
          "id": "LOF_017"
        },
        "player1Base": {
          "id": "LOF_020"
        },
        "player2Leader": {
          "id": "SEC_001"
        },
        "player2Base": {
          "id": "JTL_024"
        },
        "format": "premier"
      },
      "startTime": "2026-02-06T06:51:02.812296729-08:00"
    },
    "6aca29f3-cb6b-4af6-b9a3-1b8f1854c716": {
      "game": {
        "id": "6aca29f3-cb6b-4af6-b9a3-1b8f1854c716",
        "player1Leader": {
          "id": "SOR_014"
        },
        "player1Base": {
          "id": "SOR_022"
        },
        "player2Leader": {
          "id": "JTL_002"
        },
        "player2Base": {
          "id": "LOF_029"
        },
        "format": "premier"
      },
      "startTime": "2026-02-06T06:47:04.743988839-08:00"
    },
    "6eec0f8e-8d87-4fd5-bb88-ef13b69ae2c2": {
      "game": {
        "id": "6eec0f8e-8d87-4fd5-bb88-ef13b69ae2c2",
        "player1Leader": {
          "id": "SEC_001"
        },
        "player1Base": {
          "id": "JTL_024"
        },
        "player2Leader": {
          "id": "JTL_005"
        },
        "player2Base": {
          "id": "JTL_027"
        },
        "format": "premier"
      },
      "startTime": "2026-02-06T06:48:03.57065742-08:00"
    },
    "739eda45-1c66-4df3-9d5a-ca8ac36c1ce5": {
      "game": {
        "id": "739eda45-1c66-4df3-9d5a-ca8ac36c1ce5",
        "player1Leader": {
          "id": "LOF_009"
        },
        "player1Base": {
          "id": "LOF_020"
        },
        "player2Leader": {
          "id": "LOF_002"
        },
        "player2Base": {
          "id": "LOF_027"
        },
        "format": "premier"
      },
      "startTime": "2026-02-06T06:51:02.812296729-08:00"
    },
    "74eabe3f-a8f1-46ae-a5d1-da447518b35a": {
      "game": {
        "id": "74eabe3f-a8f1-46ae-a5d1-da447518b35a",
        "player1Leader": {
          "id": "SEC_012"
        },
        "player1Base": {
          "id": "SEC_025"
        },
        "player2Leader": {
          "id": "SOR_006"
        },
        "player2Base": {
          "id": "SOR_030"
        },
        "format": "premier"
      },
      "startTime": "2026-02-06T06:50:07.774584901-08:00"
    },
    "74f83ce3-e58e-4043-bb23-048becddaab4": {
      "game": {
        "id": "74f83ce3-e58e-4043-bb23-048becddaab4",
        "player1Leader": {
          "id": "JTL_006"
        },
        "player1Base": {
          "id": "SEC_024"
        },
        "player2Leader": {
          "id": "SEC_012"
        },
        "player2Base": {
          "id": "JTL_024"
        },
        "format": "premier"
      },
      "startTime": "2026-02-06T06:49:02.626682543-08:00"
    },
    "75967da0-5376-41df-9cd2-b22d6a0e3c29": {
      "game": {
        "id": "75967da0-5376-41df-9cd2-b22d6a0e3c29",
        "player1Leader": {
          "id": "JTL_012"
        },
        "player1Base": {
          "id": "JTL_024"
        },
        "player2Leader": {
          "id": "SHD_013"
        },
        "player2Base": {
          "id": "JTL_024"
        },
        "format": "premier"
      },
      "startTime": "2026-02-06T06:51:02.812296729-08:00"
    },
    "7a7d4f15-35a7-42ed-9ad4-5cf34ce9a38c": {
      "game": {
        "id": "7a7d4f15-35a7-42ed-9ad4-5cf34ce9a38c",
        "player1Leader": {
          "id": "SEC_017"
        },
        "player1Base": {
          "id": "SOR_025"
        },
        "player2Leader": {
          "id": "SHD_011"
        },
        "player2Base": {
          "id": "JTL_021"
        },
        "format": "premier"
      },
      "startTime": "2026-02-06T06:49:02.626682543-08:00"
    },
    "7e0f10f2-363e-4660-b096-edfda93c1687": {
      "game": {
        "id": "7e0f10f2-363e-4660-b096-edfda93c1687",
        "player1Leader": {
          "id": "LOF_002"
        },
        "player1Base": {
          "id": "LOF_029"
        },
        "player2Leader": {
          "id": "SEC_016"
        },
        "player2Base": {
          "id": "JTL_026"
        },
        "format": "nextSetPreview"
      },
      "startTime": "2026-02-06T06:44:10.039465841-08:00"
    },
    "8432e5fb-09ee-4203-bdaa-80adb1a7b3fb": {
      "game": {
        "id": "8432e5fb-09ee-4203-bdaa-80adb1a7b3fb",
        "player1Leader": {
          "id": "JTL_017"
        },
        "player1Base": {
          "id": "SOR_025"
        },
        "player2Leader": {
          "id": "SOR_008"
        },
        "player2Base": {
          "id": "JTL_031"
        },
        "format": "premier"
      },
      "startTime": "2026-02-06T06:51:02.812296729-08:00"
    },
    "85db69dc-a6f3-477c-8acc-b8cedcbae49f": {
      "game": {
        "id": "85db69dc-a6f3-477c-8acc-b8cedcbae49f",
        "player1Leader": {
          "id": "LAW_014"
        },
        "player1Base": {
          "id": "JTL_030"
        },
        "player2Leader": {
          "id": "LAW_005"
        },
        "player2Base": {
          "id": "JTL_026"
        },
        "format": "nextSetPreview"
      },
      "startTime": "2026-02-06T06:40:06.272938444-08:00"
    },
    "864daaab-d1c6-4739-8e80-dfb85d785eb9": {
      "game": {
        "id": "864daaab-d1c6-4739-8e80-dfb85d785eb9",
        "player1Leader": {
          "id": "JTL_006"
        },
        "player1Base": {
          "id": "JTL_030"
        },
        "player2Leader": {
          "id": "JTL_005"
        },
        "player2Base": {
          "id": "SOR_027"
        },
        "format": "premier"
      },
      "startTime": "2026-02-06T06:51:02.812296729-08:00"
    },
    "8aba7eb6-fb15-499b-8a64-fd6a3886e108": {
      "game": {
        "id": "8aba7eb6-fb15-499b-8a64-fd6a3886e108",
        "player1Leader": {
          "id": "LOF_008"
        },
        "player1Base": {
          "id": "LOF_019"
        },
        "player2Leader": {
          "id": "JTL_001"
        },
        "player2Base": {
          "id": "SEC_023"
        },
        "format": "nextSetPreview"
      },
      "startTime": "2026-02-06T06:51:02.812296729-08:00"
    },
    "8ad0f8c0-9f43-4aee-ab3b-ce94528fa00f": {
      "game": {
        "id": "8ad0f8c0-9f43-4aee-ab3b-ce94528fa00f",
        "player1Leader": {
          "id": "SOR_017"
        },
        "player1Base": {
          "id": "SOR_025"
        },
        "player2Leader": {
          "id": "IBH_001"
        },
        "player2Base": {
          "id": "JTL_024"
        },
        "format": "premier"
      },
      "startTime": "2026-02-06T06:49:02.626682543-08:00"
    },
    "8b293480-5b53-434d-8473-eef379c386dd": {
      "game": {
        "id": "8b293480-5b53-434d-8473-eef379c386dd",
        "player1Leader": {
          "id": "JTL_009"
        },
        "player1Base": {
          "id": "JTL_030"
        },
        "player2Leader": {
          "id": "SEC_010"
        },
        "player2Base": {
          "id": "JTL_021"
        },
        "format": "nextSetPreview"
      },
      "startTime": "2026-02-06T06:47:04.743988839-08:00"
    },
    "8b5c2465-d5db-4af7-8767-88f97a7af52f": {
      "game": {
        "id": "8b5c2465-d5db-4af7-8767-88f97a7af52f",
        "player1Leader": {
          "id": "LAW_005"
        },
        "player1Base": {
          "id": "JTL_022"
        },
        "player2Leader": {
          "id": "JTL_014"
        },
        "player2Base": {
          "id": "LOF_026"
        },
        "format": "nextSetPreview"
      },
      "startTime": "2026-02-06T06:49:02.626682543-08:00"
    },
    "8ca07427-c7e2-426e-a7c6-32d840ef786b": {
      "game": {
        "id": "8ca07427-c7e2-426e-a7c6-32d840ef786b",
        "player1Leader": {
          "id": "JTL_017"
        },
        "player1Base": {
          "id": "LAW_027"
        },
        "player2Leader": {
          "id": "LAW_008"
        },
        "player2Base": {
          "id": "JTL_030"
        },
        "format": "nextSetPreview"
      },
      "startTime": "2026-02-06T06:49:02.626682543-08:00"
    },
    "8def11b8-155d-411f-8b0d-2b928243309e": {
      "game": {
        "id": "8def11b8-155d-411f-8b0d-2b928243309e",
        "player1Leader": {
          "id": "SOR_017"
        },
        "player1Base": {
          "id": "SOR_024"
        },
        "player2Leader": {
          "id": "JTL_013"
        },
        "player2Base": {
          "id": "JTL_024"
        },
        "format": "premier"
      },
      "startTime": "2026-02-06T06:51:02.812296729-08:00"
    },
    "8f880f1e-3917-4266-91c0-4c59954914f8": {
      "game": {
        "id": "8f880f1e-3917-4266-91c0-4c59954914f8",
        "player1Leader": {
          "id": "SHD_013"
        },
        "player1Base": {
          "id": "SEC_019"
        },
        "player2Leader": {
          "id": "SHD_001"
        },
        "player2Base": {
          "id": "JTL_030"
        },
        "format": "premier"
      },
      "startTime": "2026-02-06T06:51:02.812296729-08:00"
    },
    "913c390b-b238-4883-a965-775ac85b5719": {
      "game": {
        "id": "913c390b-b238-4883-a965-775ac85b5719",
        "player1Leader": {
          "id": "SHD_013"
        },
        "player1Base": {
          "id": "LOF_021"
        },
        "player2Leader": {
          "id": "LOF_002"
        },
        "player2Base": {
          "id": "LOF_026"
        },
        "format": "premier"
      },
      "startTime": "2026-02-06T06:41:03.813659592-08:00"
    },
    "91451c81-206f-47ac-8587-70dda2326610": {
      "game": {
        "id": "91451c81-206f-47ac-8587-70dda2326610",
        "player1Leader": {
          "id": "LAW_008"
        },
        "player1Base": {
          "id": "SEC_025"
        },
        "player2Leader": {
          "id": "LOF_008"
        },
        "player2Base": {
          "id": "LOF_021"
        },
        "format": "nextSetPreview"
      },
      "startTime": "2026-02-06T06:50:07.774584901-08:00"
    },
    "99b7f01d-c2f1-4278-b8f2-fe1d09115d01": {
      "game": {
        "id": "99b7f01d-c2f1-4278-b8f2-fe1d09115d01",
        "player1Leader": {
          "id": "JTL_001"
        },
        "player1Base": {
          "id": "LOF_029"
        },
        "player2Leader": {
          "id": "SHD_014"
        },
        "player2Base": {
          "id": "SOR_025"
        },
        "format": "premier"
      },
      "startTime": "2026-02-06T06:51:02.812296729-08:00"
    },
    "9a4748e1-b6de-46d8-9e59-0fd542613e91": {
      "game": {
        "id": "9a4748e1-b6de-46d8-9e59-0fd542613e91",
        "player1Leader": {
          "id": "SHD_004"
        },
        "player1Base": {
          "id": "JTL_024"
        },
        "player2Leader": {
          "id": "SHD_001"
        },
        "player2Base": {
          "id": "SOR_022"
        },
        "format": "premier"
      },
      "startTime": "2026-02-06T06:51:02.812296729-08:00"
    },
    "9add08bb-7a9e-41fb-b987-8a443602c1ab": {
      "game": {
        "id": "9add08bb-7a9e-41fb-b987-8a443602c1ab",
        "player1Leader": {
          "id": "SEC_017"
        },
        "player1Base": {
          "id": "JTL_023"
        },
        "player2Leader": {
          "id": "JTL_006"
        },
        "player2Base": {
          "id": "SOR_029"
        },
        "format": "premier"
      },
      "startTime": "2026-02-06T06:48:03.57065742-08:00"
    },
    "9b271431-0d75-46ba-9938-e16ad0d2cdca": {
      "game": {
        "id": "9b271431-0d75-46ba-9938-e16ad0d2cdca",
        "player1Leader": {
          "id": "SEC_013"
        },
        "player1Base": {
          "id": "SHD_025"
        },
        "player2Leader": {
          "id": "SEC_017"
        },
        "player2Base": {
          "id": "SOR_025"
        },
        "format": "premier"
      },
      "startTime": "2026-02-06T06:51:02.812296729-08:00"
    },
    "9f48c4dc-1040-4d3c-a98b-6ea91357c93f": {
      "game": {
        "id": "9f48c4dc-1040-4d3c-a98b-6ea91357c93f",
        "player1Leader": {
          "id": "LAW_008"
        },
        "player1Base": {
          "id": "TWI_030"
        },
        "player2Leader": {
          "id": "LOF_010"
        },
        "player2Base": {
          "id": "LOF_029"
        },
        "format": "open"
      },
      "startTime": "2026-02-06T06:48:03.57065742-08:00"
    },
    "a6d7d2b4-27c8-419e-8e81-270a8fd505cf": {
      "game": {
        "id": "a6d7d2b4-27c8-419e-8e81-270a8fd505cf",
        "player1Leader": {
          "id": "LOF_008"
        },
        "player1Base": {
          "id": "LOF_019"
        },
        "player2Leader": {
          "id": "SEC_002"
        },
        "player2Base": {
          "id": "JTL_024"
        },
        "format": "nextSetPreview"
      },
      "startTime": "2026-02-06T06:47:04.743988839-08:00"
    },
    "aae7b205-bb8e-4e83-b314-32e0a870dd71": {
      "game": {
        "id": "aae7b205-bb8e-4e83-b314-32e0a870dd71",
        "player1Leader": {
          "id": "JTL_006"
        },
        "player1Base": {
          "id": "TWI_029"
        },
        "player2Leader": {
          "id": "SHD_013"
        },
        "player2Base": {
          "id": "JTL_024"
        },
        "format": "premier"
      },
      "startTime": "2026-02-06T06:50:07.774584901-08:00"
    },
    "abd976d8-3ffa-4438-932c-ccb7818524b3": {
      "game": {
        "id": "abd976d8-3ffa-4438-932c-ccb7818524b3",
        "player1Leader": {
          "id": "SOR_005"
        },
        "player1Base": {
          "id": "LOF_023"
        },
        "player2Leader": {
          "id": "SHD_002"
        },
        "player2Base": {
          "id": "JTL_024"
        },
        "format": "premier"
      },
      "startTime": "2026-02-06T06:42:07.056137012-08:00"
    },
    "b2b0d864-f065-4fe6-b68e-60328d59381e": {
      "game": {
        "id": "b2b0d864-f065-4fe6-b68e-60328d59381e",
        "player1Leader": {
          "id": "SHD_014"
        },
        "player1Base": {
          "id": "SOR_025"
        },
        "player2Leader": {
          "id": "LOF_001"
        },
        "player2Base": {
          "id": "JTL_024"
        },
        "format": "premier"
      },
      "startTime": "2026-02-06T06:49:02.626682543-08:00"
    },
    "bc59e06f-e030-49c1-bb9d-71864a4ac55f": {
      "game": {
        "id": "bc59e06f-e030-49c1-bb9d-71864a4ac55f",
        "player1Leader": {
          "id": "SHD_004"
        },
        "player1Base": {
          "id": "JTL_024"
        },
        "player2Leader": {
          "id": "SEC_013"
        },
        "player2Base": {
          "id": "JTL_024"
        },
        "format": "premier"
      },
      "startTime": "2026-02-06T06:38:04.15765051-08:00"
    },
    "bc6b7cb5-b9c2-4175-853a-ff19792ca1e5": {
      "game": {
        "id": "bc6b7cb5-b9c2-4175-853a-ff19792ca1e5",
        "player1Leader": {
          "id": "LAW_010"
        },
        "player1Base": {
          "id": "LAW_020"
        },
        "player2Leader": {
          "id": "LOF_007"
        },
        "player2Base": {
          "id": "JTL_020"
        },
        "format": "nextSetPreview"
      },
      "startTime": "2026-02-06T06:51:02.812296729-08:00"
    },
    "be9b009b-087c-43ab-9640-3c5d5e3776e0": {
      "game": {
        "id": "be9b009b-087c-43ab-9640-3c5d5e3776e0",
        "player1Leader": {
          "id": "SOR_006"
        },
        "player1Base": {
          "id": "SOR_025"
        },
        "player2Leader": {
          "id": "JTL_006"
        },
        "player2Base": {
          "id": "SEC_024"
        },
        "format": "premier"
      },
      "startTime": "2026-02-06T06:48:03.57065742-08:00"
    },
    "bf9ad221-b340-417b-b1da-fb778efd7c55": {
      "game": {
        "id": "bf9ad221-b340-417b-b1da-fb778efd7c55",
        "player1Leader": {
          "id": "LAW_008"
        },
        "player1Base": {
          "id": "SEC_025"
        },
        "player2Leader": {
          "id": "LAW_018"
        },
        "player2Base": {
          "id": "SEC_019"
        },
        "format": "nextSetPreview"
      },
      "startTime": "2026-02-06T06:46:07.003766694-08:00"
    },
    "c8c6df54-a4b8-4fb1-afa3-7322e9b381e1": {
      "game": {
        "id": "c8c6df54-a4b8-4fb1-afa3-7322e9b381e1",
        "player1Leader": {
          "id": "LAW_014"
        },
        "player1Base": {
          "id": "SEC_026"
        },
        "player2Leader": {
          "id": "LOF_008"
        },
        "player2Base": {
          "id": "LOF_019"
        },
        "format": "nextSetPreview"
      },
      "startTime": "2026-02-06T06:50:07.774584901-08:00"
    },
    "cc17c922-e637-4a5f-8845-4eda3020f0a4": {
      "game": {
        "id": "cc17c922-e637-4a5f-8845-4eda3020f0a4",
        "player1Leader": {
          "id": "JTL_012"
        },
        "player1Base": {
          "id": "JTL_024"
        },
        "player2Leader": {
          "id": "SHD_002"
        },
        "player2Base": {
          "id": "SEC_023"
        },
        "format": "premier"
      },
      "startTime": "2026-02-06T06:50:07.774584901-08:00"
    },
    "cfd8ba90-9a24-4388-ab16-a2bde8026e29": {
      "game": {
        "id": "cfd8ba90-9a24-4388-ab16-a2bde8026e29",
        "player1Leader": {
          "id": "LOF_008"
        },
        "player1Base": {
          "id": "LOF_021"
        },
        "player2Leader": {
          "id": "SHD_013"
        },
        "player2Base": {
          "id": "JTL_021"
        },
        "format": "premier"
      },
      "startTime": "2026-02-06T06:48:03.57065742-08:00"
    },
    "d07644f6-878d-488b-b68b-538de68de159": {
      "game": {
        "id": "d07644f6-878d-488b-b68b-538de68de159",
        "player1Leader": {
          "id": "LOF_008"
        },
        "player1Base": {
          "id": "LOF_019"
        },
        "player2Leader": {
          "id": "SEC_010"
        },
        "player2Base": {
          "id": "SEC_025"
        },
        "format": "nextSetPreview"
      },
      "startTime": "2026-02-06T06:48:03.57065742-08:00"
    },
    "d6a4fe87-8753-4e15-befa-8c046cd69a70": {
      "game": {
        "id": "d6a4fe87-8753-4e15-befa-8c046cd69a70",
        "player1Leader": {
          "id": "SOR_017"
        },
        "player1Base": {
          "id": "JTL_030"
        },
        "player2Leader": {
          "id": "JTL_009"
        },
        "player2Base": {
          "id": "SEC_025"
        },
        "format": "premier"
      },
      "startTime": "2026-02-06T06:50:07.774584901-08:00"
    },
    "d94cbb2d-8ba4-42b0-a4f6-fe3a7f576856": {
      "game": {
        "id": "d94cbb2d-8ba4-42b0-a4f6-fe3a7f576856",
        "player1Leader": {
          "id": "LAW_018"
        },
        "player1Base": {
          "id": "LOF_024"
        },
        "player2Leader": {
          "id": "LOF_002"
        },
        "player2Base": {
          "id": "LOF_029"
        },
        "format": "nextSetPreview"
      },
      "startTime": "2026-02-06T06:47:04.743988839-08:00"
    },
    "dd2e4a76-e561-4b68-bca3-7de0e45b57c7": {
      "game": {
        "id": "dd2e4a76-e561-4b68-bca3-7de0e45b57c7",
        "player1Leader": {
          "id": "TWI_012"
        },
        "player1Base": {
          "id": "LOF_020"
        },
        "player2Leader": {
          "id": "LOF_008"
        },
        "player2Base": {
          "id": "LOF_019"
        },
        "format": "premier"
      },
      "startTime": "2026-02-06T06:50:07.774584901-08:00"
    },
    "e1bb3dc7-622e-4723-bdfe-8a5ee5da5835": {
      "game": {
        "id": "e1bb3dc7-622e-4723-bdfe-8a5ee5da5835",
        "player1Leader": {
          "id": "LOF_002"
        },
        "player1Base": {
          "id": "LOF_026"
        },
        "player2Leader": {
          "id": "LOF_018"
        },
        "player2Base": {
          "id": "LOF_021"
        },
        "format": "premier"
      },
      "startTime": "2026-02-06T06:50:07.774584901-08:00"
    },
    "e4f3c6c8-6d8c-464d-a959-cdc3af57409d": {
      "game": {
        "id": "e4f3c6c8-6d8c-464d-a959-cdc3af57409d",
        "player1Leader": {
          "id": "JTL_011"
        },
        "player1Base": {
          "id": "TWI_028"
        },
        "player2Leader": {
          "id": "LOF_015"
        },
        "player2Base": {
          "id": "LOF_025"
        },
        "format": "premier"
      },
      "startTime": "2026-02-06T06:50:07.774584901-08:00"
    },
    "e788d969-47be-4a75-a45f-cc61599b1aca": {
      "game": {
        "id": "e788d969-47be-4a75-a45f-cc61599b1aca",
        "player1Leader": {
          "id": "LOF_002"
        },
        "player1Base": {
          "id": "LOF_026"
        },
        "player2Leader": {
          "id": "LAW_014"
        },
        "player2Base": {
          "id": "SOR_030"
        },
        "format": "nextSetPreview"
      },
      "startTime": "2026-02-06T06:48:03.57065742-08:00"
    },
    "e90654ec-b638-4494-92fd-57cb1b6b137f": {
      "game": {
        "id": "e90654ec-b638-4494-92fd-57cb1b6b137f",
        "player1Leader": {
          "id": "LOF_008"
        },
        "player1Base": {
          "id": "LOF_019"
        },
        "player2Leader": {
          "id": "LOF_007"
        },
        "player2Base": {
          "id": "LOF_021"
        },
        "format": "nextSetPreview"
      },
      "startTime": "2026-02-06T06:48:03.57065742-08:00"
    },
    "ea22635a-0bbd-4cac-8c44-e44177da2072": {
      "game": {
        "id": "ea22635a-0bbd-4cac-8c44-e44177da2072",
        "player1Leader": {
          "id": "JTL_005"
        },
        "player1Base": {
          "id": "JTL_020"
        },
        "player2Leader": {
          "id": "SHD_004"
        },
        "player2Base": {
          "id": "JTL_024"
        },
        "format": "premier"
      },
      "startTime": "2026-02-06T06:41:03.813659592-08:00"
    },
    "eb90c1fe-42c4-4451-86a6-a9e63a7efba9": {
      "game": {
        "id": "eb90c1fe-42c4-4451-86a6-a9e63a7efba9",
        "player1Leader": {
          "id": "LOF_009"
        },
        "player1Base": {
          "id": "LOF_021"
        },
        "player2Leader": {
          "id": "JTL_009"
        },
        "player2Base": {
          "id": "JTL_024"
        },
        "format": "premier"
      },
      "startTime": "2026-02-06T06:47:04.743988839-08:00"
    },
    "ec3a92d5-36fd-41d2-9b3a-e05667c663d4": {
      "game": {
        "id": "ec3a92d5-36fd-41d2-9b3a-e05667c663d4",
        "player1Leader": {
          "id": "LOF_008"
        },
        "player1Base": {
          "id": "LOF_019"
        },
        "player2Leader": {
          "id": "JTL_012"
        },
        "player2Base": {
          "id": "JTL_024"
        },
        "format": "premier"
      },
      "startTime": "2026-02-06T06:46:07.003766694-08:00"
    },
    "ecdc85d8-f018-46cd-bf84-38df01f8736e": {
      "game": {
        "id": "ecdc85d8-f018-46cd-bf84-38df01f8736e",
        "player1Leader": {
          "id": "SEC_017"
        },
        "player1Base": {
          "id": "SOR_025"
        },
        "player2Leader": {
          "id": "SOR_005"
        },
        "player2Base": {
          "id": "SOR_024"
        },
        "format": "premier"
      },
      "startTime": "2026-02-06T06:48:03.57065742-08:00"
    },
    "ed2ec16b-a1d8-4ff2-bfa2-c9f3a9f82665": {
      "game": {
        "id": "ed2ec16b-a1d8-4ff2-bfa2-c9f3a9f82665",
        "player1Leader": {
          "id": "SEC_017"
        },
        "player1Base": {
          "id": "SHD_024"
        },
        "player2Leader": {
          "id": "SHD_001"
        },
        "player2Base": {
          "id": "SHD_025"
        },
        "format": "premier"
      },
      "startTime": "2026-02-06T06:51:02.812296729-08:00"
    },
    "f0b1213f-d14f-48ce-ab72-9eafe22c03d4": {
      "game": {
        "id": "f0b1213f-d14f-48ce-ab72-9eafe22c03d4",
        "player1Leader": {
          "id": "LOF_001"
        },
        "player1Base": {
          "id": "JTL_024"
        },
        "player2Leader": {
          "id": "LOF_013"
        },
        "player2Base": {
          "id": "LOF_026"
        },
        "format": "premier"
      },
      "startTime": "2026-02-06T06:47:04.743988839-08:00"
    },
    "feb426e3-193a-45c6-9b18-806c56dc7335": {
      "game": {
        "id": "feb426e3-193a-45c6-9b18-806c56dc7335",
        "player1Leader": {
          "id": "TWI_005"
        },
        "player1Base": {
          "id": "LOF_020"
        },
        "player2Leader": {
          "id": "JTL_009"
        },
        "player2Base": {
          "id": "JTL_024"
        },
        "format": "premier"
      },
      "startTime": "2026-02-06T06:46:07.003766694-08:00"
    },
    "ffffacf6-380b-4983-bf3a-dc7a671f0b8b": {
      "game": {
        "id": "ffffacf6-380b-4983-bf3a-dc7a671f0b8b",
        "player1Leader": {
          "id": "LAW_008"
        },
        "player1Base": {
          "id": "LAW_020"
        },
        "player2Leader": {
          "id": "LOF_006"
        },
        "player2Base": {
          "id": "JTL_020"
        },
        "format": "nextSetPreview"
      },
      "startTime": "2026-02-06T06:49:02.626682543-08:00"
    }
  }
}
