{
  "timestamp": "2026-02-07T17:59:43.684980736-08:00",
  "games": {
    "00e66207-84a9-49d3-8d26-5e3e54770790": {
      "game": {
        "id": "00e66207-84a9-49d3-8d26-5e3e54770790",
        "player1Leader": {
          "id": "LAW_008"
        },
        "player1Base": {
          "id": "SEC_025"
        },
        "player2Leader": {
          "id": "LAW_012"
        },
        "player2Base": {
          "id": "SEC_026"
        },
        "format": "nextSetPreview",
        "gamesToWinMode": "bestOfOne"
      },
      "startTime": "2026-02-07T17:59:43.684980736-08:00"
    },
    "0210074d-3ebc-45bd-9b6c-d639574ee558": {
      "game": {
        "id": "0210074d-3ebc-45bd-9b6c-d639574ee558",
        "player1Leader": {
          "id": "LOF_002"
        },
        "player1Base": {
          "id": "LOF_027"
        },
        "player2Leader": {
          "id": "LOF_001"
        },
        "player2Base": {
          "id": "JTL_024"
        },
        "format": "premier",
        "gamesToWinMode": "bestOfOne"
      },
      "startTime": "2026-02-07T17:49:49.099207947-08:00"
    },
    "0228d348-9a55-43e7-8ce3-7d3288bc1132": {
      "game": {
        "id": "0228d348-9a55-43e7-8ce3-7d3288bc1132",
        "player1Leader": {
          "id": "SHD_010"
        },
        "player1Base": {
          "id": "SOR_025"
        },
        "player2Leader": {
          "id": "JTL_009"
        },
        "player2Base": {
          "id": "SOR_025"
        },
        "format": "premier",
        "gamesToWinMode": "bestOfOne"
      },
      "startTime": "2026-02-07T17:56:39.913459454-08:00"
    },
    "028b251e-9e6a-41f2-b3ce-4b4bdea74284": {
      "game": {
        "id": "028b251e-9e6a-41f2-b3ce-4b4bdea74284",
        "player1Leader": {
          "id": "SOR_017"
        },
        "player1Base": {
          "id": "JTL_030"
        },
        "player2Leader": {
          "id": "TWI_004"
        },
        "player2Base": {
          "id": "JTL_024"
        },
        "format": "premier",
        "gamesToWinMode": "bestOfThree"
      },
      "startTime": "2026-02-07T17:53:34.607464016-08:00"
    },
    "0e880ea0-4308-4906-86d5-63df8811df8a": {
      "game": {
        "id": "0e880ea0-4308-4906-86d5-63df8811df8a",
        "player1Leader": {
          "id": "TWI_007"
        },
        "player1Base": {
          "id": "SEC_024"
        },
        "player2Leader": {
          "id": "SOR_010"
        },
        "player2Base": {
          "id": "SHD_022"
        },
        "format": "open",
        "gamesToWinMode": "bestOfOne"
      },
      "startTime": "2026-02-07T17:47:37.700542494-08:00"
    },
    "0eb1c473-d648-4ce8-abc2-25c50b219616": {
      "game": {
        "id": "0eb1c473-d648-4ce8-abc2-25c50b219616",
        "player1Leader": {
          "id": "SEC_001"
        },
        "player1Base": {
          "id": "JTL_024"
        },
        "player2Leader": {
          "id": "LAW_001"
        },
        "player2Base": {
          "id": "SEC_019"
        },
        "format": "nextSetPreview",
        "gamesToWinMode": "bestOfOne"
      },
      "startTime": "2026-02-07T17:59:43.684980736-08:00"
    },
    "12903afd-dce9-41ba-8498-aa37700c062a": {
      "game": {
        "id": "12903afd-dce9-41ba-8498-aa37700c062a",
        "player1Leader": {
          "id": "JTL_009"
        },
        "player1Base": {
          "id": "TWI_024"
        },
        "player2Leader": {
          "id": "SHD_004"
        },
        "player2Base": {
          "id": "JTL_024"
        },
        "format": "premier",
        "gamesToWinMode": "bestOfThree"
      },
      "startTime": "2026-02-07T17:57:38.676466278-08:00"
    },
    "13832e80-5b7c-4516-996e-6aa623acc2af": {
      "game": {
        "id": "13832e80-5b7c-4516-996e-6aa623acc2af",
        "player1Leader": {
          "id": "LAW_009"
        },
        "player1Base": {
          "id": "LAW_020"
        },
        "player2Leader": {
          "id": "LAW_006"
        },
        "player2Base": {
          "id": "LAW_028"
        },
        "format": "nextSetPreview",
        "gamesToWinMode": "bestOfOne"
      },
      "startTime": "2026-02-07T17:59:43.684980736-08:00"
    },
    "1fac7693-c96c-4dca-82f3-9ea8e8c6d015": {
      "game": {
        "id": "1fac7693-c96c-4dca-82f3-9ea8e8c6d015",
        "player1Leader": {
          "id": "TWI_013"
        },
        "player1Base": {
          "id": "SOR_026"
        },
        "player2Leader": {
          "id": "LAW_014"
        },
        "player2Base": {
          "id": "SHD_026"
        },
        "format": "open",
        "gamesToWinMode": "bestOfOne"
      },
      "startTime": "2026-02-07T17:54:39.022963758-08:00"
    },
    "25df60fe-6c99-4e6f-90f7-c4327ead5d01": {
      "game": {
        "id": "25df60fe-6c99-4e6f-90f7-c4327ead5d01",
        "player1Leader": {
          "id": "JTL_005"
        },
        "player1Base": {
          "id": "SEC_024"
        },
        "player2Leader": {
          "id": "LOF_008"
        },
        "player2Base": {
          "id": "LOF_019"
        },
        "format": "premier",
        "gamesToWinMode": "bestOfOne"
      },
      "startTime": "2026-02-07T17:57:38.676466278-08:00"
    },
    "2847a8de-f29f-4858-a8dd-eac1c57294cd": {
      "game": {
        "id": "2847a8de-f29f-4858-a8dd-eac1c57294cd",
        "player1Leader": {
          "id": "SHD_004"
        },
        "player1Base": {
          "id": "JTL_024"
        },
        "player2Leader": {
          "id": "JTL_017"
        },
        "player2Base": {
          "id": "SOR_026"
        },
        "format": "premier",
        "gamesToWinMode": "bestOfOne"
      },
      "startTime": "2026-02-07T17:56:39.913459454-08:00"
    },
    "327dc624-c9f5-418c-8244-bc10b79d1a18": {
      "game": {
        "id": "327dc624-c9f5-418c-8244-bc10b79d1a18",
        "player1Leader": {
          "id": "SHD_013"
        },
        "player1Base": {
          "id": "JTL_020"
        },
        "player2Leader": {
          "id": "TWI_001"
        },
        "player2Base": {
          "id": "SOR_022"
        },
        "format": "premier",
        "gamesToWinMode": "bestOfOne"
      },
      "startTime": "2026-02-07T17:52:37.020183432-08:00"
    },
    "336e4817-563f-4311-9a7d-7b27cd65a7bf": {
      "game": {
        "id": "336e4817-563f-4311-9a7d-7b27cd65a7bf",
        "player1Leader": {
          "id": "LOF_017"
        },
        "player1Base": {
          "id": "LOF_021"
        },
        "player2Leader": {
          "id": "JTL_009"
        },
        "player2Base": {
          "id": "SOR_025"
        },
        "format": "premier",
        "gamesToWinMode": "bestOfOne"
      },
      "startTime": "2026-02-07T17:58:41.924677789-08:00"
    },
    "3bacd4f3-af90-4d27-952e-e50ee1dd3cff": {
      "game": {
        "id": "3bacd4f3-af90-4d27-952e-e50ee1dd3cff",
        "player1Leader": {
          "id": "LOF_009"
        },
        "player1Base": {
          "id": "LOF_020"
        },
        "player2Leader": {
          "id": "LAW_001"
        },
        "player2Base": {
          "id": "SOR_026"
        },
        "format": "open",
        "gamesToWinMode": "bestOfOne"
      },
      "startTime": "2026-02-07T17:58:41.924677789-08:00"
    },
    "3ed18632-c88e-47b4-9268-f2809b9246b0": {
      "game": {
        "id": "3ed18632-c88e-47b4-9268-f2809b9246b0",
        "player1Leader": {
          "id": "LAW_005"
        },
        "player1Base": {
          "id": "JTL_025"
        },
        "player2Leader": {
          "id": "JTL_009"
        },
        "player2Base": {
          "id": "JTL_030"
        },
        "format": "nextSetPreview",
        "gamesToWinMode": "bestOfOne"
      },
      "startTime": "2026-02-07T17:57:38.676466278-08:00"
    },
    "3f522bfd-f102-415a-9765-b4dbf6efaf44": {
      "game": {
        "id": "3f522bfd-f102-415a-9765-b4dbf6efaf44",
        "player1Leader": {
          "id": "SOR_014"
        },
        "player1Base": {
          "id": "SOR_022"
        },
        "player2Leader": {
          "id": "TWI_004"
        },
        "player2Base": {
          "id": "JTL_024"
        },
        "format": "premier",
        "gamesToWinMode": "bestOfThree"
      },
      "startTime": "2026-02-07T17:52:37.020183432-08:00"
    },
    "3f980ea9-409d-4e99-bdf1-2c73f7130b8b": {
      "game": {
        "id": "3f980ea9-409d-4e99-bdf1-2c73f7130b8b",
        "player1Leader": {
          "id": "SOR_006"
        },
        "player1Base": {
          "id": "JTL_021"
        },
        "player2Leader": {
          "id": "JTL_006"
        },
        "player2Base": {
          "id": "SHD_025"
        },
        "format": "premier",
        "gamesToWinMode": "bestOfOne"
      },
      "startTime": "2026-02-07T17:50:51.579562999-08:00"
    },
    "402458fb-cb99-4967-b96c-c03219fab9bb": {
      "game": {
        "id": "402458fb-cb99-4967-b96c-c03219fab9bb",
        "player1Leader": {
          "id": "SEC_006"
        },
        "player1Base": {
          "id": "SEC_024"
        },
        "player2Leader": {
          "id": "LOF_017"
        },
        "player2Base": {
          "id": "LOF_020"
        },
        "format": "premier",
        "gamesToWinMode": "bestOfOne"
      },
      "startTime": "2026-02-07T17:58:41.924677789-08:00"
    },
    "41fcee4d-29f9-4fd9-b373-d52b09b2fca2": {
      "game": {
        "id": "41fcee4d-29f9-4fd9-b373-d52b09b2fca2",
        "player1Leader": {
          "id": "SEC_017"
        },
        "player1Base": {
          "id": "JTL_030"
        },
        "player2Leader": {
          "id": "LAW_008"
        },
        "player2Base": {
          "id": "JTL_020"
        },
        "format": "nextSetPreview",
        "gamesToWinMode": "bestOfOne"
      },
      "startTime": "2026-02-07T17:57:38.676466278-08:00"
    },
    "423b91ed-05d3-4415-8190-2e612d9528be": {
      "game": {
        "id": "423b91ed-05d3-4415-8190-2e612d9528be",
        "player1Leader": {
          "id": "LOF_013"
        },
        "player1Base": {
          "id": "LOF_021"
        },
        "player2Leader": {
          "id": "JTL_017"
        },
        "player2Base": {
          "id": "JTL_027"
        },
        "format": "nextSetPreview",
        "gamesToWinMode": "bestOfOne"
      },
      "startTime": "2026-02-07T17:55:42.564015503-08:00"
    },
    "4472920f-3bab-4761-867c-45c1c3e8cf25": {
      "game": {
        "id": "4472920f-3bab-4761-867c-45c1c3e8cf25",
        "player1Leader": {
          "id": "LAW_010"
        },
        "player1Base": {
          "id": "LAW_020"
        },
        "player2Leader": {
          "id": "JTL_017"
        },
        "player2Base": {
          "id": "JTL_027"
        },
        "format": "open",
        "gamesToWinMode": "bestOfOne"
      },
      "startTime": "2026-02-07T17:58:41.924677789-08:00"
    },
    "478eebf7-83f7-4822-9c71-98b6d5adc85e": {
      "game": {
        "id": "478eebf7-83f7-4822-9c71-98b6d5adc85e",
        "player1Leader": {
          "id": "LOF_016"
        },
        "player1Base": {
          "id": "LOF_029"
        },
        "player2Leader": {
          "id": "SHD_013"
        },
        "player2Base": {
          "id": "TWI_026"
        },
        "format": "premier",
        "gamesToWinMode": "bestOfOne"
      },
      "startTime": "2026-02-07T17:55:42.564015503-08:00"
    },
    "490d3bd9-fd20-4f5a-b508-14784c6f9d7b": {
      "game": {
        "id": "490d3bd9-fd20-4f5a-b508-14784c6f9d7b",
        "player1Leader": {
          "id": "JTL_006"
        },
        "player1Base": {
          "id": "SHD_025"
        },
        "player2Leader": {
          "id": "JTL_012"
        },
        "player2Base": {
          "id": "JTL_024"
        },
        "format": "premier",
        "gamesToWinMode": "bestOfOne"
      },
      "startTime": "2026-02-07T17:55:42.564015503-08:00"
    },
    "4991ad55-e99b-453f-b57d-34a4cf783449": {
      "game": {
        "id": "4991ad55-e99b-453f-b57d-34a4cf783449",
        "player1Leader": {
          "id": "TWI_012"
        },
        "player1Base": {
          "id": "JTL_021"
        },
        "player2Leader": {
          "id": "SEC_005"
        },
        "player2Base": {
          "id": "JTL_024"
        },
        "format": "premier",
        "gamesToWinMode": "bestOfOne"
      },
      "startTime": "2026-02-07T17:56:39.913459454-08:00"
    },
    "4f7a2586-f0cf-4c06-a818-203b998a5039": {
      "game": {
        "id": "4f7a2586-f0cf-4c06-a818-203b998a5039",
        "player1Leader": {
          "id": "JTL_006"
        },
        "player1Base": {
          "id": "SOR_023"
        },
        "player2Leader": {
          "id": "LOF_008"
        },
        "player2Base": {
          "id": "LOF_030"
        },
        "format": "premier",
        "gamesToWinMode": "bestOfOne"
      },
      "startTime": "2026-02-07T17:56:39.913459454-08:00"
    },
    "51a2a369-2cf3-4eb7-8de3-f3c099387ec8": {
      "game": {
        "id": "51a2a369-2cf3-4eb7-8de3-f3c099387ec8",
        "player1Leader": {
          "id": "TWI_002"
        },
        "player1Base": {
          "id": "SHD_025"
        },
        "player2Leader": {
          "id": "SEC_001"
        },
        "player2Base": {
          "id": "JTL_024"
        },
        "format": "open",
        "gamesToWinMode": "bestOfOne"
      },
      "startTime": "2026-02-07T17:41:09.139421953-08:00"
    },
    "53d8f5b8-164e-4a72-8d49-9f1141586d62": {
      "game": {
        "id": "53d8f5b8-164e-4a72-8d49-9f1141586d62",
        "player1Leader": {
          "id": "TWI_012"
        },
        "player1Base": {
          "id": "JTL_024"
        },
        "player2Leader": {
          "id": "SHD_014"
        },
        "player2Base": {
          "id": "SOR_025"
        },
        "format": "premier",
        "gamesToWinMode": "bestOfThree"
      },
      "startTime": "2026-02-07T17:55:42.564015503-08:00"
    },
    "5584fc3d-b426-4bd1-88fe-9b99b91ff957": {
      "game": {
        "id": "5584fc3d-b426-4bd1-88fe-9b99b91ff957",
        "player1Leader": {
          "id": "SHD_001"
        },
        "player1Base": {
          "id": "SOR_022"
        },
        "player2Leader": {
          "id": "SOR_002"
        },
        "player2Base": {
          "id": "JTL_024"
        },
        "format": "premier",
        "gamesToWinMode": "bestOfOne"
      },
      "startTime": "2026-02-07T17:56:39.913459454-08:00"
    },
    "56c139d0-8407-4611-b7b3-b3e69dd79a5b": {
      "game": {
        "id": "56c139d0-8407-4611-b7b3-b3e69dd79a5b",
        "player1Leader": {
          "id": "JTL_008"
        },
        "player1Base": {
          "id": "JTL_028"
        },
        "player2Leader": {
          "id": "TWI_005"
        },
        "player2Base": {
          "id": "JTL_024"
        },
        "format": "premier",
        "gamesToWinMode": "bestOfOne"
      },
      "startTime": "2026-02-07T17:59:43.684980736-08:00"
    },
    "65acca0a-04d4-45b1-9c8c-3d54ffca1263": {
      "game": {
        "id": "65acca0a-04d4-45b1-9c8c-3d54ffca1263",
        "player1Leader": {
          "id": "JTL_005"
        },
        "player1Base": {
          "id": "SOR_026"
        },
        "player2Leader": {
          "id": "JTL_006"
        },
        "player2Base": {
          "id": "SEC_025"
        },
        "format": "premier",
        "gamesToWinMode": "bestOfOne"
      },
      "startTime": "2026-02-07T17:59:43.684980736-08:00"
    },
    "78061817-1078-42c0-a343-e647d571c087": {
      "game": {
        "id": "78061817-1078-42c0-a343-e647d571c087",
        "player1Leader": {
          "id": "LAW_014"
        },
        "player1Base": {
          "id": "SEC_019"
        },
        "player2Leader": {
          "id": "LAW_006"
        },
        "player2Base": {
          "id": "LOF_019"
        },
        "format": "nextSetPreview",
        "gamesToWinMode": "bestOfOne"
      },
      "startTime": "2026-02-07T17:58:41.924677789-08:00"
    },
    "78a025e7-73ef-45a8-aa76-3674da67794e": {
      "game": {
        "id": "78a025e7-73ef-45a8-aa76-3674da67794e",
        "player1Leader": {
          "id": "SHD_012"
        },
        "player1Base": {
          "id": "SOR_029"
        },
        "player2Leader": {
          "id": "TWI_018"
        },
        "player2Base": {
          "id": "LOF_026"
        },
        "format": "premier",
        "gamesToWinMode": "bestOfOne"
      },
      "startTime": "2026-02-07T17:57:38.676466278-08:00"
    },
    "7ca77bce-bea3-436b-aed5-eccf39b2a57c": {
      "game": {
        "id": "7ca77bce-bea3-436b-aed5-eccf39b2a57c",
        "player1Leader": {
          "id": "LAW_008"
        },
        "player1Base": {
          "id": "SEC_025"
        },
        "player2Leader": {
          "id": "LAW_015"
        },
        "player2Base": {
          "id": "LAW_023"
        },
        "format": "nextSetPreview",
        "gamesToWinMode": "bestOfOne"
      },
      "startTime": "2026-02-07T17:55:42.564015503-08:00"
    },
    "81c9ddff-e1a9-4e31-b864-8563600b6ff0": {
      "game": {
        "id": "81c9ddff-e1a9-4e31-b864-8563600b6ff0",
        "player1Leader": {
          "id": "SEC_008"
        },
        "player1Base": {
          "id": "JTL_024"
        },
        "player2Leader": {
          "id": "LOF_008"
        },
        "player2Base": {
          "id": "LOF_022"
        },
        "format": "premier",
        "gamesToWinMode": "bestOfOne"
      },
      "startTime": "2026-02-07T17:53:34.607464016-08:00"
    },
    "858da0a8-1c17-4d36-a1ea-9e6b33c2d63f": {
      "game": {
        "id": "858da0a8-1c17-4d36-a1ea-9e6b33c2d63f",
        "player1Leader": {
          "id": "SEC_006"
        },
        "player1Base": {
          "id": "LAW_028"
        },
        "player2Leader": {
          "id": "LOF_015"
        },
        "player2Base": {
          "id": "LOF_023"
        },
        "format": "nextSetPreview",
        "gamesToWinMode": "bestOfOne"
      },
      "startTime": "2026-02-07T17:58:41.924677789-08:00"
    },
    "88023a15-0d3d-4bc0-a506-8af2dbba916e": {
      "game": {
        "id": "88023a15-0d3d-4bc0-a506-8af2dbba916e",
        "player1Leader": {
          "id": "SOR_006"
        },
        "player1Base": {
          "id": "SOR_020"
        },
        "player2Leader": {
          "id": "SHD_001"
        },
        "player2Base": {
          "id": "LOF_030"
        },
        "format": "premier",
        "gamesToWinMode": "bestOfOne"
      },
      "startTime": "2026-02-07T17:57:38.676466278-08:00"
    },
    "8a3ef447-3071-4da3-93a6-0c02da9ceb5a": {
      "game": {
        "id": "8a3ef447-3071-4da3-93a6-0c02da9ceb5a",
        "player1Leader": {
          "id": "LAW_001"
        },
        "player1Base": {
          "id": "SEC_026"
        },
        "player2Leader": {
          "id": "LAW_012"
        },
        "player2Base": {
          "id": "SEC_026"
        },
        "format": "nextSetPreview",
        "gamesToWinMode": "bestOfOne"
      },
      "startTime": "2026-02-07T17:55:42.564015503-08:00"
    },
    "8a80775a-1c24-4639-b795-23de63586a1f": {
      "game": {
        "id": "8a80775a-1c24-4639-b795-23de63586a1f",
        "player1Leader": {
          "id": "JTL_009"
        },
        "player1Base": {
          "id": "JTL_024"
        },
        "player2Leader": {
          "id": "TWI_012"
        },
        "player2Base": {
          "id": "JTL_031"
        },
        "format": "premier",
        "gamesToWinMode": "bestOfOne"
      },
      "startTime": "2026-02-07T17:59:43.684980736-08:00"
    },
    "8ed00c07-4100-4e4c-9395-d98f99fd1768": {
      "game": {
        "id": "8ed00c07-4100-4e4c-9395-d98f99fd1768",
        "player1Leader": {
          "id": "SEC_016"
        },
        "player1Base": {
          "id": "SEC_024"
        },
        "player2Leader": {
          "id": "JTL_018"
        },
        "player2Base": {
          "id": "LAW_022"
        },
        "format": "nextSetPreview",
        "gamesToWinMode": "bestOfOne"
      },
      "startTime": "2026-02-07T17:45:37.328221707-08:00"
    },
    "905cdb69-7be4-450f-a0e3-8d92e9bc822a": {
      "game": {
        "id": "905cdb69-7be4-450f-a0e3-8d92e9bc822a",
        "player1Leader": {
          "id": "LOF_015"
        },
        "player1Base": {
          "id": "LOF_023"
        },
        "player2Leader": {
          "id": "JTL_008"
        },
        "player2Base": {
          "id": "JTL_028"
        },
        "format": "premier",
        "gamesToWinMode": "bestOfOne"
      },
      "startTime": "2026-02-07T17:59:43.684980736-08:00"
    },
    "9208f455-1d4b-42cf-8b37-cd53effa61c2": {
      "game": {
        "id": "9208f455-1d4b-42cf-8b37-cd53effa61c2",
        "player1Leader": {
          "id": "TWI_013"
        },
        "player1Base": {
          "id": "JTL_026"
        },
        "player2Leader": {
          "id": "SEC_010"
        },
        "player2Base": {
          "id": "TWI_023"
        },
        "format": "premier",
        "gamesToWinMode": "bestOfOne"
      },
      "startTime": "2026-02-07T17:55:42.564015503-08:00"
    },
    "962a86ef-8a2e-4c3e-b992-8547b4ac50db": {
      "game": {
        "id": "962a86ef-8a2e-4c3e-b992-8547b4ac50db",
        "player1Leader": {
          "id": "LAW_005"
        },
        "player1Base": {
          "id": "JTL_025"
        },
        "player2Leader": {
          "id": "LAW_006"
        },
        "player2Base": {
          "id": "SEC_021"
        },
        "format": "nextSetPreview",
        "gamesToWinMode": "bestOfOne"
      },
      "startTime": "2026-02-07T17:57:38.676466278-08:00"
    },
    "967e48dc-691b-4ffa-9c34-e92f4eeea2dd": {
      "game": {
        "id": "967e48dc-691b-4ffa-9c34-e92f4eeea2dd",
        "player1Leader": {
          "id": "SHD_004"
        },
        "player1Base": {
          "id": "LOF_021"
        },
        "player2Leader": {
          "id": "SOR_013"
        },
        "player2Base": {
          "id": "JTL_030"
        },
        "format": "premier",
        "gamesToWinMode": "bestOfOne"
      },
      "startTime": "2026-02-07T17:54:39.022963758-08:00"
    },
    "99f8d142-b45a-464b-9d7a-e919c5bfe2fd": {
      "game": {
        "id": "99f8d142-b45a-464b-9d7a-e919c5bfe2fd",
        "player1Leader": {
          "id": "JTL_009"
        },
        "player1Base": {
          "id": "JTL_031"
        },
        "player2Leader": {
          "id": "SHD_014"
        },
        "player2Base": {
          "id": "JTL_024"
        },
        "format": "premier",
        "gamesToWinMode": "bestOfOne"
      },
      "startTime": "2026-02-07T17:53:34.607464016-08:00"
    },
    "9e0fb847-9c8e-45c3-92e9-1b35f971c79c": {
      "game": {
        "id": "9e0fb847-9c8e-45c3-92e9-1b35f971c79c",
        "player1Leader": {
          "id": "LOF_008"
        },
        "player1Base": {
          "id": "LOF_026"
        },
        "player2Leader": {
          "id": "SHD_013"
        },
        "player2Base": {
          "id": "JTL_024"
        },
        "format": "premier",
        "gamesToWinMode": "bestOfThree"
      },
      "startTime": "2026-02-07T17:50:51.579562999-08:00"
    },
    "a254a7f4-0d92-41d0-915c-ff4e252cc804": {
      "game": {
        "id": "a254a7f4-0d92-41d0-915c-ff4e252cc804",
        "player1Leader": {
          "id": "SEC_017"
        },
        "player1Base": {
          "id": "SOR_025"
        },
        "player2Leader": {
          "id": "LOF_009"
        },
        "player2Base": {
          "id": "LOF_020"
        },
        "format": "premier",
        "gamesToWinMode": "bestOfOne"
      },
      "startTime": "2026-02-07T17:59:43.684980736-08:00"
    },
    "ab93c3ef-13e4-412a-a9f8-803da7e64927": {
      "game": {
        "id": "ab93c3ef-13e4-412a-a9f8-803da7e64927",
        "player1Leader": {
          "id": "SEC_017"
        },
        "player1Base": {
          "id": "SEC_021"
        },
        "player2Leader": {
          "id": "JTL_012"
        },
        "player2Base": {
          "id": "JTL_022"
        },
        "format": "premier",
        "gamesToWinMode": "bestOfOne"
      },
      "startTime": "2026-02-07T17:55:42.564015503-08:00"
    },
    "b3ccb512-6ee2-4676-9816-f5bdf183777a": {
      "game": {
        "id": "b3ccb512-6ee2-4676-9816-f5bdf183777a",
        "player1Leader": {
          "id": "LOF_007"
        },
        "player1Base": {
          "id": "LOF_029"
        },
        "player2Leader": {
          "id": "LAW_001"
        },
        "player2Base": {
          "id": "SEC_020"
        },
        "format": "nextSetPreview",
        "gamesToWinMode": "bestOfOne"
      },
      "startTime": "2026-02-07T17:57:38.676466278-08:00"
    },
    "b98ecc8b-9185-4efd-bb9c-18ab7953c716": {
      "game": {
        "id": "b98ecc8b-9185-4efd-bb9c-18ab7953c716",
        "player1Leader": {
          "id": "TWI_012"
        },
        "player1Base": {
          "id": "JTL_024"
        },
        "player2Leader": {
          "id": "SEC_014"
        },
        "player2Base": {
          "id": "JTL_024"
        },
        "format": "premier",
        "gamesToWinMode": "bestOfThree"
      },
      "startTime": "2026-02-07T17:49:49.099207947-08:00"
    },
    "bea572b1-6a46-4d45-a904-60e3b7f1ea87": {
      "game": {
        "id": "bea572b1-6a46-4d45-a904-60e3b7f1ea87",
        "player1Leader": {
          "id": "SEC_010"
        },
        "player1Base": {
          "id": "JTL_021"
        },
        "player2Leader": {
          "id": "LOF_017"
        },
        "player2Base": {
          "id": "LOF_020"
        },
        "format": "nextSetPreview",
        "gamesToWinMode": "bestOfOne"
      },
      "startTime": "2026-02-07T17:57:38.676466278-08:00"
    },
    "c132fa73-3ea1-4c67-800a-01e29d3edb0e": {
      "game": {
        "id": "c132fa73-3ea1-4c67-800a-01e29d3edb0e",
        "player1Leader": {
          "id": "LAW_003"
        },
        "player1Base": {
          "id": "JTL_024"
        },
        "player2Leader": {
          "id": "SEC_010"
        },
        "player2Base": {
          "id": "SEC_019"
        },
        "format": "nextSetPreview",
        "gamesToWinMode": "bestOfOne"
      },
      "startTime": "2026-02-07T17:54:39.022963758-08:00"
    },
    "c18a100a-a869-4098-9a91-2acbaad0bad2": {
      "game": {
        "id": "c18a100a-a869-4098-9a91-2acbaad0bad2",
        "player1Leader": {
          "id": "JTL_006"
        },
        "player1Base": {
          "id": "JTL_030"
        },
        "player2Leader": {
          "id": "SEC_017"
        },
        "player2Base": {
          "id": "SOR_025"
        },
        "format": "premier",
        "gamesToWinMode": "bestOfOne"
      },
      "startTime": "2026-02-07T17:53:34.607464016-08:00"
    },
    "c54ca4ef-480e-4a5d-a309-474d7dd6a2bf": {
      "game": {
        "id": "c54ca4ef-480e-4a5d-a309-474d7dd6a2bf",
        "player1Leader": {
          "id": "LAW_008"
        },
        "player1Base": {
          "id": "JTL_021"
        },
        "player2Leader": {
          "id": "LAW_012"
        },
        "player2Base": {
          "id": "JTL_030"
        },
        "format": "nextSetPreview",
        "gamesToWinMode": "bestOfOne"
      },
      "startTime": "2026-02-07T17:56:39.913459454-08:00"
    },
    "c7edc485-5264-4593-a291-3b8d8b42c2b7": {
      "game": {
        "id": "c7edc485-5264-4593-a291-3b8d8b42c2b7",
        "player1Leader": {
          "id": "SHD_013"
        },
        "player1Base": {
          "id": "SOR_022"
        },
        "player2Leader": {
          "id": "SOR_017"
        },
        "player2Base": {
          "id": "SEC_025"
        },
        "format": "premier",
        "gamesToWinMode": "bestOfOne"
      },
      "startTime": "2026-02-07T17:59:43.684980736-08:00"
    },
    "c8cde312-4df1-400d-a18f-393648b534b0": {
      "game": {
        "id": "c8cde312-4df1-400d-a18f-393648b534b0",
        "player1Leader": {
          "id": "JTL_005"
        },
        "player1Base": {
          "id": "JTL_020"
        },
        "player2Leader": {
          "id": "LOF_013"
        },
        "player2Base": {
          "id": "LOF_020"
        },
        "format": "nextSetPreview",
        "gamesToWinMode": "bestOfOne"
      },
      "startTime": "2026-02-07T17:56:39.913459454-08:00"
    },
    "d149833c-8b2b-49e8-8003-b870330f2520": {
      "game": {
        "id": "d149833c-8b2b-49e8-8003-b870330f2520",
        "player1Leader": {
          "id": "LAW_001"
        },
        "player1Base": {
          "id": "JTL_019"
        },
        "player2Leader": {
          "id": "LAW_001"
        },
        "player2Base": {
          "id": "SEC_025"
        },
        "format": "nextSetPreview",
        "gamesToWinMode": "bestOfOne"
      },
      "startTime": "2026-02-07T17:58:41.924677789-08:00"
    },
    "d1ede2b9-464f-49d8-93c2-e99ea6bfe945": {
      "game": {
        "id": "d1ede2b9-464f-49d8-93c2-e99ea6bfe945",
        "player1Leader": {
          "id": "TWI_004"
        },
        "player1Base": {
          "id": "JTL_024"
        },
        "player2Leader": {
          "id": "SOR_016"
        },
        "player2Base": {
          "id": "JTL_021"
        },
        "format": "premier",
        "gamesToWinMode": "bestOfOne"
      },
      "startTime": "2026-02-07T17:50:51.579562999-08:00"
    },
    "da80a585-6979-4ab9-8b65-9dd3b7b63944": {
      "game": {
        "id": "da80a585-6979-4ab9-8b65-9dd3b7b63944",
        "player1Leader": {
          "id": "JTL_003"
        },
        "player1Base": {
          "id": "JTL_024"
        },
        "player2Leader": {
          "id": "JTL_005"
        },
        "player2Base": {
          "id": "JTL_027"
        },
        "format": "premier",
        "gamesToWinMode": "bestOfOne"
      },
      "startTime": "2026-02-07T17:48:34.97790605-08:00"
    },
    "e1f805ee-59ab-437b-97b1-360b4d8e125b": {
      "game": {
        "id": "e1f805ee-59ab-437b-97b1-360b4d8e125b",
        "player1Leader": {
          "id": "JTL_006"
        },
        "player1Base": {
          "id": "JTL_020"
        },
        "player2Leader": {
          "id": "SOR_017"
        },
        "player2Base": {
          "id": "SOR_025"
        },
        "format": "premier",
        "gamesToWinMode": "bestOfOne"
      },
      "startTime": "2026-02-07T17:56:39.913459454-08:00"
    },
    "e8874077-0e0f-4e73-a04a-1d6ae07fa8c5": {
      "game": {
        "id": "e8874077-0e0f-4e73-a04a-1d6ae07fa8c5",
        "player1Leader": {
          "id": "SEC_006"
        },
        "player1Base": {
          "id": "SEC_023"
        },
        "player2Leader": {
          "id": "TWI_003"
        },
        "player2Base": {
          "id": "TWI_021"
        },
        "format": "premier",
        "gamesToWinMode": "bestOfOne"
      },
      "startTime": "2026-02-07T17:58:41.924677789-08:00"
    },
    "ea5fcb48-b657-4d3f-806a-6a18d3accf91": {
      "game": {
        "id": "ea5fcb48-b657-4d3f-806a-6a18d3accf91",
        "player1Leader": {
          "id": "LAW_008"
        },
        "player1Base": {
          "id": "LAW_028"
        },
        "player2Leader": {
          "id": "LOF_018"
        },
        "player2Base": {
          "id": "LOF_021"
        },
        "format": "nextSetPreview",
        "gamesToWinMode": "bestOfOne"
      },
      "startTime": "2026-02-07T17:59:43.684980736-08:00"
    },
    "ec9e5b24-cccb-4121-8926-11b7b2a83d6c": {
      "game": {
        "id": "ec9e5b24-cccb-4121-8926-11b7b2a83d6c",
        "player1Leader": {
          "id": "LOF_008"
        },
        "player1Base": {
          "id": "LOF_026"
        },
        "player2Leader": {
          "id": "LAW_001"
        },
        "player2Base": {
          "id": "JTL_019"
        },
        "format": "nextSetPreview",
        "gamesToWinMode": "bestOfOne"
      },
      "startTime": "2026-02-07T17:57:38.676466278-08:00"
    },
    "ece9d01a-ba0b-4d24-bb0f-5bb1572beee1": {
      "game": {
        "id": "ece9d01a-ba0b-4d24-bb0f-5bb1572beee1",
        "player1Leader": {
          "id": "LOF_015"
        },
        "player1Base": {
          "id": "LOF_027"
        },
        "player2Leader": {
          "id": "JTL_009"
        },
        "player2Base": {
          "id": "JTL_020"
        },
        "format": "premier",
        "gamesToWinMode": "bestOfOne"
      },
      "startTime": "2026-02-07T17:54:39.022963758-08:00"
    },
    "fba7ea64-9308-4c40-a425-83e821438676": {
      "game": {
        "id": "fba7ea64-9308-4c40-a425-83e821438676",
        "player1Leader": {
          "id": "SOR_015"
        },
        "player1Base": {
          "id": "JTL_024"
        },
        "player2Leader": {
          "id": "LOF_009"
        },
        "player2Base": {
          "id": "LOF_020"
        },
        "format": "open",
        "gamesToWinMode": "bestOfOne"
      },
      "startTime": "2026-02-07T17:59:43.684980736-08:00"
    },
    "fcce894d-72de-43fd-8f87-9eef204df59a": {
      "game": {
        "id": "fcce894d-72de-43fd-8f87-9eef204df59a",
        "player1Leader": {
          "id": "SEC_017"
        },
        "player1Base": {
          "id": "JTL_024"
        },
        "player2Leader": {
          "id": "JTL_008"
        },
        "player2Base": {
          "id": "JTL_028"
        },
        "format": "nextSetPreview",
        "gamesToWinMode": "bestOfOne"
      },
      "startTime": "2026-02-07T17:56:39.913459454-08:00"
    },
    "fe91af9b-2e3b-4df2-a8ce-841e2092d1af": {
      "game": {
        "id": "fe91af9b-2e3b-4df2-a8ce-841e2092d1af",
        "player1Leader": {
          "id": "LAW_001"
        },
        "player1Base": {
          "id": "SEC_026"
        },
        "player2Leader": {
          "id": "LOF_007"
        },
        "player2Base": {
          "id": "LOF_029"
        },
        "format": "nextSetPreview",
        "gamesToWinMode": "bestOfOne"
      },
      "startTime": "2026-02-07T17:58:41.924677789-08:00"
    },
    "fe9c9364-4e9d-4abd-9ff0-1acb70fbb690": {
      "game": {
        "id": "fe9c9364-4e9d-4abd-9ff0-1acb70fbb690",
        "player1Leader": {
          "id": "TWI_004"
        },
        "player1Base": {
          "id": "JTL_024"
        },
        "player2Leader": {
          "id": "SOR_017"
        },
        "player2Base": {
          "id": "JTL_023"
        },
        "format": "premier",
        "gamesToWinMode": "bestOfOne"
      },
      "startTime": "2026-02-07T17:55:42.564015503-08:00"
    },
    "feed2fd3-0a83-4655-9931-8858bffb1f5b": {
      "game": {
        "id": "feed2fd3-0a83-4655-9931-8858bffb1f5b",
        "player1Leader": {
          "id": "SEC_002"
        },
        "player1Base": {
          "id": "SHD_022"
        },
        "player2Leader": {
          "id": "LOF_006"
        },
        "player2Base": {
          "id": "SOR_027"
        },
        "format": "premier",
        "gamesToWinMode": "bestOfOne"
      },
      "startTime": "2026-02-07T17:48:34.97790605-08:00"
    }
  }
}
